mcp_tianditu/__init__.py
mcp_tianditu/__main__.py
mcp_tianditu/server.py
mcp_tianditu/tdapi.py
mcp_tianditu/util.py
mcp_tianditu/resources/AdminCode.txt
mcp_tianditu/resources/Type.txt
mcp_server_tianditu-0.1.1.dist-info/METADATA
mcp_server_tianditu-0.1.1.dist-info/WHEEL
mcp_server_tianditu-0.1.1.dist-info/entry_points.txt
mcp_server_tianditu-0.1.1.dist-info/top_level.txt
mcp_server_tianditu-0.1.1.dist-info/RECORD
