Metadata-Version: 2.4
Name: mcp-server-tianditu
Version: 0.1.1
Summary: 天地图MCP服务
Author-email: baihe <bailaohe@gmail.com>
Requires-Python: >=3.10
Requires-Dist: mcp[cli]>=1.6.0
Requires-Dist: httpx
